LICENSE.txt
MANIFEST.in
README.md
pyproject.toml
setup.cfg
setup.py
kioblog/__init__.py
kioblog/admin.py
kioblog/apps.py
kioblog/context_preprocessors.py
kioblog/decorators.py
kioblog/models.py
kioblog/sitemap.py
kioblog/urls.py
kioblog/views.py
kioblog.egg-info/PKG-INFO
kioblog.egg-info/SOURCES.txt
kioblog.egg-info/dependency_links.txt
kioblog.egg-info/requires.txt
kioblog.egg-info/top_level.txt
kioblog/migrations/0001_initial.py
kioblog/migrations/0002_auto_20220724_1836.py
kioblog/migrations/0003_auto_20220809_1735.py
kioblog/migrations/__init__.py
kioblog/static/kioblog/css/custom.css
kioblog/templates/kioblog/base.html
kioblog/templates/kioblog/home.html
kioblog/templates/kioblog/post.html
kioblog/templates/kioblog/includes/footer.html
kioblog/templates/kioblog/includes/header.html
kioblog/templates/kioblog/includes/sidebar.html
kioblog/tests/__init__.py
kioblog/tests/base.py
kioblog/tests/test_models.py
kioblog/tests/test_views.py