Metadata-Version: 2.1
Name: kioblog
Version: 0.1.4a0
Summary: Simple blog for Django
Home-page: https://github.com/Eric-Bujeque/kioblog
Download-URL: https://github.com/Eric-Bujeque/kioblog/archive/refs/tags/v0.1.4-alpha.tar.gz
Author: Eric Bujeque
Author-email: noikzyr3@gmail.com
License: MIT
Keywords: blog,django
Classifier: Development Status :: 3 - Alpha
Classifier: Intended Audience :: Developers
Classifier: Topic :: Software Development :: Libraries :: Python Modules
Classifier: License :: OSI Approved :: MIT License
Classifier: Programming Language :: Python :: 3
Classifier: Programming Language :: Python :: 3.8
Classifier: Programming Language :: Python :: 3.9
Classifier: Programming Language :: Python :: 3.10
Classifier: Programming Language :: Python :: 3.11
Classifier: Programming Language :: Python :: 3.12
License-File: LICENSE.txt
Requires-Dist: Django>=5.1
Requires-Dist: django-robots>=6.1
Requires-Dist: django-summernote>=0.8.20.0
